{
  "book": "\u0392\u0384 \u0392\u0391\u03a3\u0399\u039b\u0395\u03a9\u039d (\u03ae \u0392\u0391\u03a3\u0399\u039b\u0395\u0399\u03a9\u039d \u0394\u0384)",
  "chapter": 25,
  "1": [
    [
      "\u0388\u03c4\u03c3\u03b9",
      "Thus"
    ],
    [
      "\u03c4\u03b7",
      "the (fem. acc. sing.)"
    ],
    [
      "\u03b4\u03ad\u03ba\u03b1\u03c4\u03b7",
      "tenth"
    ],
    [
      "\u03bc\u03ad\u03c1\u03b1",
      "day"
    ],
    [
      "\u03c4\u03bf\u03c5",
      "of the (masc. gen. sing.)"
    ],
    [
      "\u03b4\u03ad\u03ba\u03b1\u03c4\u03bf\u03c5",
      "tenth (masc. gen. sing.)"
    ],
    [
      "\u03bc\u03ae\u03bd\u03b1",
      "month"
    ],
    [
      "\u03c4\u03bf\u03c5",
      "of the (masc. gen. sing.)"
    ],
    [
      "\u03ad\u03bd\u03b1\u03c4\u03bf\u03c5",
      "ninth (masc. gen. sing.)"
    ],
    [
      "\u03ad\u03c4\u03bf\u03c5\u03c2",
      "year"
    ],
    [
      "\u03c4\u03b7\u03c2",
      "of the (fem. gen. sing.)"
    ],
    [
      "\u03b2\u03b1\u03c3\u03b9\u03bb\u03b5\u03af\u03b1\u03c2",
      "reign/kingdom"
    ],
    [
      "\u03c4\u03bf\u03c5",
      "of the (masc. gen. sing.)"
    ],
    [
      "\u03a3\u03b5\u03b4\u03b5\u03ba\u03af\u03b1",
      "Zedekiah (proper name),"
    ],
    [
      "\u03bf",
      "the (masc. nom. sing.)"
    ],
    [
      "\u039d\u03b1\u03b2\u03bf\u03c5\u03c7\u03bf\u03b4\u03bf\u03bd\u03cc\u03c3\u03bf\u03c1",
      "Nebuchadnezzar (proper name)"
    ],
    [
      "\u03ae\u03c1\u03b8\u03b5",
      "came"
    ],
    [
      "\u03bc\u03b5",
      "with"
    ],
    [
      "\u03cc\u03bb\u03bf",
      "all"
    ],
    [
      "\u03c4\u03bf",
      "the (neut. acc. sing.)"
    ],
    [
      "\u03c3\u03c4\u03c1\u03b1\u03c4\u03cc",
      "army"
    ],
    [
      "\u03c4\u03bf\u03c5",
      "his"
    ],
    [
      "\u03c3\u03c4\u03b7\u03bd",
      "to the (fem. acc. sing.)"
    ],
    [
      "\u0399\u03b5\u03c1\u03bf\u03c5\u03c3\u03b1\u03bb\u03ae\u03bc",
      "Jerusalem;"
    ],
    [
      "\u03c3\u03c4\u03c1\u03b1\u03c4\u03bf\u03c0\u03ad\u03b4\u03b5\u03c5\u03c3\u03b5",
      "he camped"
    ],
    [
      "\u03b1\u03c0\u03ad\u03bd\u03b1\u03bd\u03c4\u03af",
      "opposite"
    ],
    [
      "\u03c4\u03b7\u03c2",
      "it (fem. gen. sing.)"
    ],
    [
      "\u03ba\u03b1\u03b9",
      "and"
    ],
    [
      "\u03ba\u03b1\u03c4\u03b1\u03c3\u03ba\u03b5\u03cd\u03b1\u03c3\u03b5",
      "he built"
    ],
    [
      "\u03c0\u03bf\u03bb\u03b9\u03bf\u03c1\u03ba\u03b7\u03c4\u03b9\u03ba\u03cc",
      "siege (adj.)"
    ],
    [
      "\u03c4\u03b5\u03af\u03c7\u03bf\u03c2",
      "wall"
    ],
    [
      "\u03b3\u03cd\u03c1\u03c9",
      "around"
    ],
    [
      "\u03b1\u03c0\u03cc",
      "from"
    ],
    [
      "\u03c4\u03b7\u03bd",
      "the (fem. acc. sing.)"
    ],
    [
      "\u03c0\u03cc\u03bb\u03b7",
      "city"
    ]
  ],
  "2": [
    [
      "\u0397",
      "The"
    ],
    [
      "\u03c0\u03bf\u03bb\u03b9\u03bf\u03c1\u03ba\u03af\u03b1",
      "siege"
    ],
    [
      "\u03ba\u03c1\u03ac\u03c4\u03b7\u03c3\u03b5",
      "held"
    ],
    [
      "\u03c9\u03c2",
      "until"
    ],
    [
      "\u03c4\u03bf",
      "the"
    ],
    [
      "\u03b5\u03bd\u03b4\u03ad\u03ba\u03b1\u03c4\u03bf",
      "eleventh"
    ],
    [
      "\u03ad\u03c4\u03bf\u03c2",
      "year"
    ],
    [
      "\u03c4\u03b7\u03c2",
      "of the"
    ],
    [
      "\u03b2\u03b1\u03c3\u03b9\u03bb\u03b5\u03af\u03b1\u03c2",
      "reign"
    ],
    [
      "\u03c4\u03bf\u03c5",
      "of the"
    ],
    [
      "\u03a3\u03b5\u03b4\u03b5\u03ba\u03af\u03b1",
      "Sedeqiah"
    ]
  ],
  "3": [
    [
      "\u03bf\u03c0\u03cc\u03c4\u03b5",
      "therefore"
    ],
    [
      "\u03ad\u03c0\u03b5\u03c3\u03b5",
      "fell"
    ],
    [
      "\u03c0\u03bf\u03bb\u03cd",
      "very"
    ],
    [
      "\u03bc\u03b5\u03b3\u03ac\u03bb\u03b7",
      "big"
    ],
    [
      "\u03c0\u03b5\u03af\u03bd\u03b1",
      "hunger"
    ],
    [
      "\u03c3\u03c4\u03b7\u03bd",
      "in the"
    ],
    [
      "\u03c0\u03cc\u03bb\u03b7\u0387",
      "city;"
    ],
    [
      "\u03b4\u03b5\u03bd",
      "not"
    ],
    [
      "\u03c5\u03c0\u03ae\u03c1\u03c7\u03b5",
      "there was"
    ],
    [
      "\u03ba\u03b1\u03b8\u03cc\u03bb\u03bf\u03c5",
      "at all"
    ],
    [
      "\u03c4\u03c1\u03bf\u03c6\u03ae",
      "food"
    ],
    [
      "\u03b3\u03b9\u03b1",
      "for"
    ],
    [
      "\u03c4\u03bf\u03c5\u03c2",
      "the"
    ],
    [
      "\u03ba\u03b1\u03c4\u03bf\u03af\u03ba\u03bf\u03c5\u03c2",
      "inhabitants"
    ],
    [
      "\u03c4\u03b7\u03c2.",
      "of it."
    ],
    [
      "\u03a4\u03cc\u03c4\u03b5,",
      "Then,"
    ],
    [
      "\u03c4\u03b7\u03bd",
      "the"
    ],
    [
      "\u03ad\u03bd\u03b1\u03c4\u03b7",
      "ninth"
    ],
    [
      "\u03bc\u03ad\u03c1\u03b1",
      "day"
    ],
    [
      "\u03c4\u03bf\u03c5",
      "of the"
    ],
    [
      "\u03c4\u03ad\u03c4\u03b1\u03c1\u03c4\u03bf\u03c5",
      "fourth"
    ],
    [
      "\u03bc\u03ae\u03bd\u03b1,",
      "month,"
    ]
  ],
  "4": [
    [
      "\u03bf\u03b9",
      "the"
    ],
    [
      "\u0392\u03b1\u03b2\u03c5\u03bb\u03ce\u03bd\u03b9\u03bf\u03b9",
      "Babylonians"
    ],
    [
      "\u03ad\u03ba\u03b1\u03bd\u03b1\u03bd",
      "made/did"
    ],
    [
      "\u03ad\u03bd\u03b1",
      "a"
    ],
    [
      "\u03ac\u03bd\u03bf\u03b9\u03b3\u03bc\u03b1",
      "opening"
    ],
    [
      "\u03c3\u03c4\u03bf",
      "in the"
    ],
    [
      "\u03c4\u03b5\u03af\u03c7\u03bf\u03c2",
      "wall"
    ],
    [
      "\u03c4\u03b7\u03c2",
      "of the"
    ],
    [
      "\u03c0\u03cc\u03bb\u03b7\u03c2.",
      "city."
    ],
    [
      "\u03a4\u03b7",
      "The"
    ],
    [
      "\u03bd\u03cd\u03c7\u03c4\u03b1,",
      "night,"
    ],
    [
      "\u03bf",
      "the"
    ],
    [
      "\u03b2\u03b1\u03c3\u03b9\u03bb\u03b9\u03ac\u03c2",
      "king"
    ],
    [
      "\u03ba\u03b1\u03b9",
      "and"
    ],
    [
      "\u03bf\u03b9",
      "the"
    ],
    [
      "\u03c0\u03bf\u03bb\u03b5\u03bc\u03b9\u03c3\u03c4\u03ad\u03c2",
      "warriors"
    ],
    [
      "\u03c4\u03bf\u03c5",
      "of the"
    ],
    [
      "\u0399\u03bf\u03cd\u03b4\u03b1",
      "Judah"
    ],
    [
      "\u03b2\u03b3\u03ae\u03ba\u03b1\u03bd",
      "went out"
    ],
    [
      "\u03b1\u03c0\u03cc",
      "from"
    ],
    [
      "\u03c4\u03bf",
      "the"
    ],
    [
      "\u03b4\u03b9\u03ac\u03b4\u03c1\u03bf\u03bc\u03bf",
      "corridor"
    ],
    [
      "\u03c0\u03bf\u03c5",
      "that"
    ],
    [
      "\u03ad\u03bd\u03c9\u03bd\u03b5",
      "connected"
    ],
    [
      "\u03c4\u03b1",
      "the"
    ],
    [
      "\u03b4\u03cd\u03bf",
      "two"
    ],
    [
      "\u03c4\u03b5\u03af\u03c7\u03b7,",
      "walls,"
    ],
    [
      "\u03c0\u03ad\u03c1\u03b1\u03c3\u03b1\u03bd",
      "passed"
    ],
    [
      "\u03ba\u03bf\u03bd\u03c4\u03ac",
      "close"
    ],
    [
      "\u03b1\u03c0\u03cc",
      "to/by"
    ],
    [
      "\u03c4\u03bf",
      "the"
    ],
    [
      "\u03b2\u03b1\u03c3\u03b9\u03bb\u03b9\u03ba\u03cc",
      "royal"
    ],
    [
      "\u03ba\u03ae\u03c0\u03bf",
      "garden"
    ],
    [
      "\u03ba\u03b1\u03b9",
      "and"
    ],
    [
      "\u03c0\u03ae\u03c1\u03b1\u03bd",
      "took"
    ],
    [
      "\u03c4\u03bf",
      "the"
    ],
    [
      "\u03b4\u03c1\u03cc\u03bc\u03bf",
      "road"
    ],
    [
      "\u03c0\u03c1\u03bf\u03c2",
      "towards"
    ],
    [
      "\u03c4\u03b7\u03bd",
      "the"
    ],
    [
      "\u03ba\u03bf\u03b9\u03bb\u03ac\u03b4\u03b1",
      "valley"
    ],
    [
      "\u03c4\u03bf\u03c5",
      "of the"
    ],
    [
      "\u0399\u03bf\u03c1\u03b4\u03ac\u03bd\u03b7,",
      "Jordan,"
    ],
    [
      "\u03c0\u03b1\u03c1\u2019",
      "although"
    ],
    [
      "\u03cc\u03bb\u03bf",
      "all"
    ],
    [
      "\u03c0\u03bf\u03c5",
      "that"
    ],
    [
      "\u03bf\u03b9",
      "the"
    ],
    [
      "\u0392\u03b1\u03b2\u03c5\u03bb\u03ce\u03bd\u03b9\u03bf\u03b9",
      "Babylonians"
    ],
    [
      "\u03b5\u03af\u03c7\u03b1\u03bd",
      "had"
    ],
    [
      "\u03c0\u03b5\u03c1\u03b9\u03ba\u03c5\u03ba\u03bb\u03ce\u03c3\u03b5\u03b9",
      "surrounded"
    ],
    [
      "\u03c4\u03b7\u03bd",
      "the"
    ],
    [
      "\u03c0\u03cc\u03bb\u03b7.",
      ""
    ]
  ],
  "5": [
    [
      "\u0391\u03bb\u03bb\u03ac",
      "But"
    ],
    [
      "\u03bf",
      "the"
    ],
    [
      "\u03b2\u03b1\u03b2\u03c5\u03bb\u03c9\u03bd\u03b9\u03b1\u03ba\u03cc\u03c2",
      "Babylonian"
    ],
    [
      "\u03c3\u03c4\u03c1\u03b1\u03c4\u03cc\u03c2",
      "army"
    ],
    [
      "\u03ba\u03b1\u03c4\u03b1\u03b4\u03af\u03c9\u03be\u03b5",
      "pursued"
    ],
    [
      "\u03c4\u03bf",
      "the"
    ],
    [
      "\u03b2\u03b1\u03c3\u03b9\u03bb\u03b9\u03ac",
      "king"
    ],
    [
      "\u03ba\u03b1\u03b9",
      "and"
    ],
    [
      "\u03c4\u03bf\u03bd",
      "him"
    ],
    [
      "\u03c0\u03c1\u03cc\u03c6\u03c4\u03b1\u03c3\u03b5",
      "overtook"
    ],
    [
      "\u03c3\u03c4\u03b9\u03c2",
      "in the"
    ],
    [
      "\u03c0\u03b5\u03b4\u03b9\u03ac\u03b4\u03b5\u03c2",
      "plains"
    ],
    [
      "\u03c4\u03b7\u03c2",
      "of the"
    ],
    [
      "\u0399\u03b5\u03c1\u03b9\u03c7\u03ce",
      "Jericho"
    ],
    [
      "\u0387:;",
      ""
    ],
    [
      "\u03c4\u03cc\u03c4\u03b5",
      "then"
    ],
    [
      "\u03cc\u03bb\u03bf\u03b9",
      "all"
    ],
    [
      "\u03bf\u03b9",
      "the"
    ],
    [
      "\u03c3\u03c4\u03c1\u03b1\u03c4\u03b9\u03ce\u03c4\u03b5\u03c2",
      "soldiers"
    ],
    [
      "\u03c4\u03bf\u03c5",
      "his"
    ],
    [
      "\u03c4\u03bf\u03bd",
      "him"
    ],
    [
      "\u03b5\u03b3\u03ba\u03b1\u03c4\u03ad\u03bb\u03b5\u03b9\u03c8\u03b1\u03bd",
      "abandoned"
    ],
    [
      "\u03ba\u03b1\u03b9",
      "and"
    ],
    [
      "\u03b4\u03b9\u03b1\u03c3\u03ba\u03bf\u03c1\u03c0\u03af\u03c3\u03c4\u03b7\u03ba\u03b1\u03bd",
      "scattered"
    ]
  ],
  "6": [
    [
      "\u039f\u03b9",
      "The"
    ],
    [
      "\u0392\u03b1\u03b2\u03c5\u03bb\u03ce\u03bd\u03b9\u03bf\u03b9",
      "Babylonians"
    ],
    [
      "\u03c3\u03c5\u03bd\u03ad\u03bb\u03b1\u03b2\u03b1\u03bd",
      "arrested"
    ],
    [
      "\u03c4\u03bf",
      "the"
    ],
    [
      "\u03a3\u03b5\u03b4\u03b5\u03ba\u03af\u03b1",
      "Zedekiah"
    ],
    [
      "\u03ba\u03b1\u03b9",
      "and"
    ],
    [
      "\u03c4\u03bf\u03bd",
      "the"
    ],
    [
      "\u03ad\u03c6\u03b5\u03c1\u03b1\u03bd",
      "brought"
    ],
    [
      "\u03c3\u03c4\u03bf",
      "to the"
    ],
    [
      "\u03b2\u03b1\u03c3\u03b9\u03bb\u03b9\u03ac",
      "king"
    ],
    [
      "\u03c4\u03b7\u03c2",
      "of the"
    ],
    [
      "\u0392\u03b1\u03b2\u03c5\u03bb\u03ce\u03bd\u03b1\u03c2",
      "Babylon"
    ],
    [
      "\u03c3\u03c4\u03b7",
      "in the"
    ],
    [
      "\u03a1\u03b9\u03b2\u03bb\u03ac",
      "Riblah"
    ],
    [
      "\u03ba\u03b9",
      "and"
    ],
    [
      "\u03b5\u03ba\u03b5\u03af\u03bd\u03bf\u03c2",
      "he"
    ],
    [
      "\u03ad\u03b2\u03b3\u03b1\u03bb\u03b5",
      "issued"
    ],
    [
      "\u03ba\u03b1\u03c4\u03b1\u03b4\u03b9\u03ba\u03b1\u03c3\u03c4\u03b9\u03ba\u03ae",
      "condemnatory"
    ],
    [
      "\u03b1\u03c0\u03cc\u03c6\u03b1\u03c3\u03b7",
      "decision"
    ],
    [
      "\u03b5\u03bd\u03b1\u03bd\u03c4\u03af\u03bf\u03bd",
      "against"
    ],
    [
      "\u03c4\u03bf\u03c5",
      "him"
    ]
  ],
  "7": [
    [
      "#",
      "VALUE!"
    ]
  ],
  "8": [
    [
      "\u03a4\u03b7\u03bd",
      "The"
    ],
    [
      "\u03ad\u03b2\u03b4\u03bf\u03bc\u03b7",
      "seventh"
    ],
    [
      "\u03bc\u03ad\u03c1\u03b1",
      "day"
    ],
    [
      "\u03c4\u03bf\u03c5",
      "of the"
    ],
    [
      "\u03c0\u03ad\u03bc\u03c0\u03c4\u03bf\u03c5",
      "fifth"
    ],
    [
      "\u03bc\u03ae\u03bd\u03b1,",
      "month,"
    ],
    [
      "\u03c4\u03bf",
      "the"
    ],
    [
      "\u03b4\u03ad\u03ba\u03b1\u03c4\u03bf",
      "tenth"
    ],
    [
      "\u03ad\u03bd\u03b1\u03c4\u03bf",
      "nineteenth"
    ],
    [
      "\u03ad\u03c4\u03bf\u03c2",
      "year"
    ],
    [
      "\u03c4\u03b7\u03c2",
      "of the"
    ],
    [
      "\u03b2\u03b1\u03c3\u03b9\u03bb\u03b5\u03af\u03b1\u03c2",
      "reign"
    ],
    [
      "\u03c4\u03bf\u03c5",
      "of the"
    ],
    [
      "\u039d\u03b1\u03b2\u03bf\u03c5\u03c7\u03bf\u03b4\u03bf\u03bd\u03cc\u03c3\u03bf\u03c1,",
      "Nebuchadnezzar,"
    ],
    [
      "\u03b2\u03b1\u03c3\u03b9\u03bb\u03b9\u03ac",
      "king"
    ],
    [
      "\u03c4\u03b7\u03c2",
      "of the"
    ],
    [
      "\u0392\u03b1\u03b2\u03c5\u03bb\u03ce\u03bd\u03b1\u03c2,",
      "Babylon,"
    ],
    [
      "\u03ae\u03c1\u03b8\u03b5",
      "came"
    ],
    [
      "\u03c3\u03c4\u03b7\u03bd",
      "to the"
    ],
    [
      "\u0399\u03b5\u03c1\u03bf\u03c5\u03c3\u03b1\u03bb\u03ae\u03bc",
      "Jerusalem"
    ],
    [
      "\u03bf",
      "the"
    ],
    [
      "\u039d\u03b5\u03b2\u03bf\u03c5\u03b6\u03b1\u03c1\u03b1\u03b4\u03ac\u03bd,",
      "Nebuzaradan,"
    ],
    [
      "\u03b1\u03c1\u03c7\u03b7\u03b3\u03cc\u03c2",
      "chief"
    ],
    [
      "\u03c4\u03b7\u03c2",
      "of the"
    ],
    [
      "\u03c3\u03c9\u03bc\u03b1\u03c4\u03bf\u03c6\u03c5\u03bb\u03b1\u03ba\u03ae\u03c2",
      "bodyguard"
    ],
    [
      "\u03c4\u03bf\u03c5.",
      "his"
    ]
  ],
  "9": [
    [
      "\u0391\u03c5\u03c4\u03cc\u03c2",
      "He"
    ],
    [
      "\u03ad\u03b2\u03b1\u03bb\u03b5",
      "put"
    ],
    [
      "\u03c6\u03c9\u03c4\u03b9\u03ac",
      "fire"
    ],
    [
      "\u03c3\u03c4\u03bf",
      "to the"
    ],
    [
      "\u03bd\u03b1\u03cc",
      "temple"
    ],
    [
      "\u03c4\u03bf\u03c5",
      "of the"
    ],
    [
      "\u039a\u03c5\u03c1\u03af\u03bf\u03c5",
      "Lord,"
    ],
    [
      "\u03c3\u03c4\u03b1",
      "in the"
    ],
    [
      "\u03b1\u03bd\u03ac\u03ba\u03c4\u03bf\u03c1\u03b1",
      "palaces"
    ],
    [
      "\u03ba\u03b1\u03b9",
      "and"
    ],
    [
      "\u03c3\u2019",
      "in"
    ],
    [
      "\u03cc\u03bb\u03b1",
      "all"
    ],
    [
      "\u03c4\u03b1",
      "the"
    ],
    [
      "\u03c3\u03c0\u03af\u03c4\u03b9\u03b1",
      "houses"
    ],
    [
      "\u03c4\u03b7\u03c2",
      "of the"
    ],
    [
      "\u0399\u03b5\u03c1\u03bf\u03c5\u03c3\u03b1\u03bb\u03ae\u03bc",
      "Jerusalem,"
    ],
    [
      "\u03b9\u03b4\u03b9\u03b1\u03af\u03c4\u03b5\u03c1\u03b1",
      "especially"
    ],
    [
      "\u03c3\u03c4\u03b1",
      "in the"
    ],
    [
      "\u03b1\u03c1\u03c7\u03bf\u03bd\u03c4\u03b9\u03ba\u03ac",
      "mansion houses"
    ],
    [
      "\u03c4\u03b7\u03c2",
      "of the"
    ],
    [
      "\u03c0\u03cc\u03bb\u03b7\u03c2",
      "city."
    ]
  ],
  "10": [
    [
      "\u03a4\u03b1",
      "The"
    ],
    [
      "\u03b2\u03b1\u03b2\u03c5\u03bb\u03c9\u03bd\u03b9\u03b1\u03ba\u03ac",
      "Babylonian"
    ],
    [
      "\u03c3\u03c4\u03c1\u03b1\u03c4\u03b5\u03cd\u03bc\u03b1\u03c4\u03b1",
      "troops"
    ],
    [
      "\u03c0\u03bf\u03c5",
      "that"
    ],
    [
      "\u03c4\u03bf\u03bd",
      "him"
    ],
    [
      "\u03b1\u03ba\u03bf\u03bb\u03bf\u03c5\u03b8\u03bf\u03cd\u03c3\u03b1\u03bd",
      "were following"
    ],
    [
      "\u03b3\u03ba\u03c1\u03ad\u03bc\u03b9\u03c3\u03b1\u03bd",
      "destroyed"
    ],
    [
      "\u03c4\u03b1",
      "the"
    ],
    [
      "\u03c4\u03b5\u03af\u03c7\u03b7",
      "walls"
    ],
    [
      "\u03c4\u03b7\u03c2",
      "of the"
    ],
    [
      "\u0399\u03b5\u03c1\u03bf\u03c5\u03c3\u03b1\u03bb\u03ae\u03bc",
      "Jerusalem"
    ]
  ],
  "11": [
    [
      "\u039a\u03b1\u03b9",
      "And"
    ],
    [
      "\u03ad\u03c3\u03c5\u03c1\u03b5",
      "drew"
    ],
    [
      "\u03bf",
      "the"
    ],
    [
      "\u039d\u03b5\u03b2\u03bf\u03c5\u03b6\u03b1\u03c1\u03b1\u03b4\u03ac\u03bd",
      "Nebuzaradan"
    ],
    [
      "\u03c3\u03c4\u03b7\u03bd",
      "to the"
    ],
    [
      "\u03b1\u03b9\u03c7\u03bc\u03b1\u03bb\u03c9\u03c3\u03af\u03b1",
      "captivity"
    ],
    [
      "\u03c4\u03bf",
      "the"
    ],
    [
      "\u03c5\u03c0\u03cc\u03bb\u03bf\u03b9\u03c0\u03bf",
      "remainder"
    ],
    [
      "\u03c4\u03bf\u03c5",
      "of the"
    ],
    [
      "\u03bb\u03b1\u03bf\u03cd",
      "people"
    ],
    [
      "\u03c0\u03bf\u03c5",
      "who"
    ],
    [
      "\u03b5\u03af\u03c7\u03b5",
      "had"
    ],
    [
      "\u03b1\u03c0\u03bf\u03bc\u03b5\u03af\u03bd\u03b5\u03b9",
      "remained"
    ],
    [
      "\u03c3\u03c4\u03b7\u03bd",
      "in the"
    ],
    [
      "\u03c0\u03cc\u03bb\u03b7",
      "city"
    ],
    [
      "\u03cc\u03bb\u03bf\u03c5\u03c2",
      "all"
    ],
    [
      "\u03cc\u03c3\u03bf\u03b9",
      "who"
    ],
    [
      "\u03b5\u03af\u03c7\u03b1\u03bd",
      "had"
    ],
    [
      "\u03b1\u03c5\u03c4\u03bf\u03bc\u03bf\u03bb\u03ae\u03c3\u03b5\u03b9",
      "defected"
    ],
    [
      "\u03c0\u03c1\u03bf\u03c2",
      "towards"
    ],
    [
      "\u03c4\u03bf",
      "the"
    ],
    [
      "\u03b2\u03b1\u03c3\u03b9\u03bb\u03b9\u03ac",
      "king"
    ],
    [
      "\u03c4\u03b7\u03c2",
      "of the"
    ],
    [
      "\u0392\u03b1\u03b2\u03c5\u03bb\u03ce\u03bd\u03b1\u03c2",
      "Babylon"
    ]
  ],
  "12": [
    [
      "\u0391\u03bb\u03bb\u03ac",
      "But"
    ],
    [
      "\u03bc\u03b5\u03c1\u03b9\u03ba\u03bf\u03cd\u03c2",
      "some"
    ],
    [
      "\u03b1\u03c0\u03cc",
      "of"
    ],
    [
      "\u03c4\u03bf\u03c5\u03c2",
      "the"
    ],
    [
      "\u03c6\u03c4\u03c9\u03c7\u03cc\u03c4\u03b5\u03c1\u03bf\u03c5\u03c2",
      "poorer"
    ],
    [
      "\u03c4\u03b7\u03c2",
      "of the"
    ],
    [
      "\u03c7\u03ce\u03c1\u03b1\u03c2",
      "country"
    ],
    [
      "\u03c4\u03bf\u03cd\u03c2",
      "them"
    ],
    [
      "\u03ac\u03c6\u03b7\u03c3\u03b5",
      "left"
    ],
    [
      "\u03c0\u03af\u03c3\u03c9",
      "behind"
    ],
    [
      "\u03b3\u03b9\u03b1",
      "to"
    ],
    [
      "\u03bd\u03b1",
      "to"
    ],
    [
      "\u03ba\u03b1\u03bb\u03bb\u03b9\u03b5\u03c1\u03b3\u03bf\u03cd\u03bd",
      "cultivate"
    ],
    [
      "\u03c4\u03b1",
      "the"
    ],
    [
      "\u03b1\u03bc\u03c0\u03ad\u03bb\u03b9\u03b1",
      "vineyards"
    ],
    [
      "\u03ba\u03b1\u03b9",
      "and"
    ],
    [
      "\u03c4\u03b1",
      "the"
    ],
    [
      "\u03c7\u03c9\u03c1\u03ac\u03c6\u03b9\u03b1",
      "fields"
    ]
  ],
  "13": [
    [
      "\u039f\u03b9",
      "The"
    ],
    [
      "\u0392\u03b1\u03b2\u03c5\u03bb\u03ce\u03bd\u03b9\u03bf\u03b9",
      "Babylonians"
    ],
    [
      "\u03ad\u03c3\u03c0\u03b1\u03c3\u03b1\u03bd",
      "broke"
    ],
    [
      "\u03c4\u03bf\u03c5\u03c2",
      "the"
    ],
    [
      "\u03c7\u03ac\u03bb\u03ba\u03b9\u03bd\u03bf\u03c5\u03c2",
      "copper"
    ],
    [
      "\u03c3\u03c4\u03cd\u03bb\u03bf\u03c5\u03c2",
      "pillars"
    ],
    [
      "\u03c4\u03bf\u03c5",
      "of the"
    ],
    [
      "\u03bd\u03b1\u03bf\u03cd",
      "temple"
    ],
    [
      "\u03c4\u03bf\u03c5",
      "of the"
    ],
    [
      "\u039a\u03c5\u03c1\u03af\u03bf\u03c5",
      "Lord"
    ],
    [
      "\u03c4\u03b9\u03c2",
      "the"
    ],
    [
      "\u03b2\u03ac\u03c3\u03b5\u03b9\u03c2",
      "bases"
    ],
    [
      "\u03ba\u03b1\u03b9",
      "and"
    ],
    [
      "\u03c4\u03b7",
      "the"
    ],
    [
      "\u03c7\u03ac\u03bb\u03ba\u03b9\u03bd\u03b7",
      "copper"
    ],
    [
      "\u03bb\u03b5\u03ba\u03ac\u03bd\u03b7",
      "bowl"
    ],
    [
      "\u03ba\u03b1\u03b9",
      "and"
    ],
    [
      "\u03bc\u03b5\u03c4\u03ad\u03c6\u03b5\u03c1\u03b1\u03bd",
      "carried"
    ],
    [
      "\u03c4\u03bf\u03bd",
      "the"
    ],
    [
      "\u03c7\u03b1\u03bb\u03ba\u03cc",
      "copper"
    ],
    [
      "\u03c4\u03bf\u03c5\u03c2",
      "their"
    ],
    [
      "\u03c3\u03c4\u03b7",
      "to the"
    ],
    [
      "\u0392\u03b1\u03b2\u03c5\u03bb\u03ce\u03bd\u03b1",
      "Babylon"
    ]
  ],
  "14": [
    [
      "\u0395\u03c0\u03af\u03c3\u03b7\u03c2",
      "Also"
    ],
    [
      "\u03c0\u03ae\u03c1\u03b1\u03bd",
      "took"
    ],
    [
      "\u03c4\u03bf\u03c5\u03c2",
      "the"
    ],
    [
      "\u03bb\u03ad\u03b2\u03b7\u03c4\u03b5\u03c2",
      "boilers"
    ],
    [
      "\u03c4\u03b1",
      "the"
    ],
    [
      "\u03c6\u03c4\u03c5\u03ac\u03c1\u03b9\u03b1",
      "shovels"
    ],
    [
      "\u03c4\u03b1",
      "the"
    ],
    [
      "\u03bb\u03c5\u03c7\u03bd\u03bf\u03c8\u03ac\u03bb\u03b9\u03b4\u03b1",
      "oil lamp scissors"
    ],
    [
      "\u03c4\u03b1",
      "the"
    ],
    [
      "\u03b8\u03c5\u03bc\u03b9\u03b1\u03c4\u03ae\u03c1\u03b9\u03b1",
      "thuribles"
    ],
    [
      "\u03ba\u03b1\u03b9",
      "and"
    ],
    [
      "\u03cc\u03bb\u03b1",
      "all"
    ],
    [
      "\u03c4\u03b1",
      "the"
    ],
    [
      "\u03c7\u03ac\u03bb\u03ba\u03b9\u03bd\u03b1",
      "copper"
    ],
    [
      "\u03c3\u03ba\u03b5\u03cd\u03b7",
      "vessels"
    ],
    [
      "\u03c0\u03bf\u03c5",
      "that"
    ],
    [
      "\u03c7\u03c1\u03b7\u03c3\u03af\u03bc\u03b5\u03c5\u03b1\u03bd",
      "were used"
    ],
    [
      "\u03b3\u03b9\u03b1",
      "for"
    ],
    [
      "\u03c4\u03b7",
      "the"
    ],
    [
      "\u03bb\u03b1\u03c4\u03c1\u03b5\u03af\u03b1",
      "worship"
    ],
    [
      "\u03c3\u03c4\u03bf",
      "in the"
    ],
    [
      "\u03bd\u03b1\u03cc",
      "temple"
    ]
  ],
  "15": [
    [
      "\u0395\u03c0\u03af\u03c3\u03b7\u03c2",
      "Also"
    ],
    [
      "\u03c0\u03ae\u03c1\u03b1\u03bd",
      "took"
    ],
    [
      "\u03c4\u03b9\u03c2",
      "the (feminine plural)"
    ],
    [
      "\u03c3\u03c7\u03ac\u03c1\u03b5\u03c2",
      "grids"
    ],
    [
      "\u03ba\u03b1\u03b9",
      "and"
    ],
    [
      "\u03c4\u03b9\u03c2",
      "the (feminine plural)"
    ],
    [
      "\u03bb\u03b5\u03ba\u03ac\u03bd\u03b5\u03c2",
      "basins"
    ],
    [
      "\u03ba\u03b1\u03b9",
      "and"
    ],
    [
      "\u03b3\u03b5\u03bd\u03b9\u03ba\u03ac",
      "generally"
    ],
    [
      "\u03cc,\u03c4\u03b9",
      "whatever"
    ],
    [
      "\u03ae\u03c4\u03b1\u03bd",
      "was"
    ],
    [
      "\u03c7\u03c1\u03c5\u03c3\u03cc",
      "gold (adjective)"
    ],
    [
      "\u03ae",
      "or"
    ],
    [
      "\u03b1\u03c3\u03b7\u03bc\u03ad\u03bd\u03b9\u03bf",
      "silver (adjective)"
    ],
    [
      "\u2014:\u2014",
      ""
    ],
    [
      "\u03c4\u03bf",
      "the (neuter singular)"
    ],
    [
      "\u03c0\u03ae\u03c1\u03b1\u03bd",
      "took"
    ],
    [
      "\u03b3\u03b9\u03b1",
      "for"
    ],
    [
      "\u03c4\u03bf",
      "the (neuter singular)"
    ],
    [
      "\u03c7\u03c1\u03c5\u03c3\u03ac\u03c6\u03b9",
      "gold (noun)"
    ],
    [
      "\u03ba\u03b1\u03b9",
      "and"
    ],
    [
      "\u03c4\u03bf",
      "the (neuter singular)"
    ],
    [
      "\u03b1\u03c3\u03ae\u03bc\u03b9",
      "silver (noun)"
    ]
  ],
  "16": [
    [
      "\u0389\u03c4\u03b1\u03bd",
      "was"
    ],
    [
      "\u03b1\u03b4\u03cd\u03bd\u03b1\u03c4\u03bf",
      "impossible"
    ],
    [
      "\u03bd\u03b1",
      "to"
    ],
    [
      "\u03b6\u03c5\u03b3\u03b9\u03c3\u03c4\u03b5\u03af",
      "be weighed"
    ],
    [
      "\u03bf",
      "the"
    ],
    [
      "\u03c7\u03b1\u03bb\u03ba\u03cc\u03c2",
      "copper"
    ],
    [
      "\u03cc\u03bb\u03c9\u03bd",
      "of all"
    ],
    [
      "\u03b1\u03c5\u03c4\u03ce\u03bd",
      "these"
    ],
    [
      "\u03c4\u03c9\u03bd",
      "the"
    ],
    [
      "\u03b1\u03bd\u03c4\u03b9\u03ba\u03b5\u03b9\u03bc\u03ad\u03bd\u03c9\u03bd",
      "objects"
    ],
    [
      ",",
      ""
    ],
    [
      "\u03b4\u03b7\u03bb\u03b1\u03b4\u03ae",
      "that is"
    ],
    [
      "\u03c4\u03c9\u03bd",
      "of the"
    ],
    [
      "\u03b4\u03cd\u03bf",
      "two"
    ],
    [
      "\u03c3\u03c4\u03cd\u03bb\u03c9\u03bd",
      "pillars"
    ],
    [
      ",",
      ""
    ],
    [
      "\u03c4\u03b7\u03c2",
      "of the"
    ],
    [
      "\u03c7\u03ac\u03bb\u03ba\u03b9\u03bd\u03b7\u03c2",
      "bronze"
    ],
    [
      "\u03bb\u03b5\u03ba\u03ac\u03bd\u03b7\u03c2",
      "basin"
    ],
    [
      "\u03ba\u03b1\u03b9",
      "and"
    ],
    [
      "\u03c4\u03c9\u03bd",
      "of the"
    ],
    [
      "\u03b2\u03ac\u03c3\u03b5\u03c9\u03bd",
      "bases"
    ],
    [
      ",",
      ""
    ],
    [
      "\u03c0\u03bf\u03c5",
      "which"
    ],
    [
      "\u03c4\u03b1",
      "them"
    ],
    [
      "\u03b5\u03af\u03c7\u03b5",
      "had"
    ],
    [
      "\u03ba\u03b1\u03c4\u03b1\u03c3\u03ba\u03b5\u03c5\u03ac\u03c3\u03b5\u03b9",
      "made"
    ],
    [
      "\u03bf",
      "the"
    ],
    [
      "\u03a3\u03bf\u03bb\u03bf\u03bc\u03ce\u03bd\u03c4\u03b1\u03c2",
      "Solomon"
    ],
    [
      "\u03b3\u03b9\u03b1",
      "for"
    ],
    [
      "\u03c4\u03bf",
      "the"
    ],
    [
      "\u03bd\u03b1\u03cc",
      "temple"
    ],
    [
      "\u03c4\u03bf\u03c5",
      "of the"
    ],
    [
      "\u039a\u03c5\u03c1\u03af\u03bf\u03c5",
      "Lord ."
    ]
  ],
  "17": [
    [
      "\u03a4\u03bf",
      "The"
    ],
    [
      "\u03cd\u03c8\u03bf\u03c2",
      "height"
    ],
    [
      "\u03c4\u03bf\u03c5",
      "of the"
    ],
    [
      "\u03ba\u03ac\u03b8\u03b5",
      "each"
    ],
    [
      "\u03c3\u03c4\u03cd\u03bb\u03bf\u03c5",
      "column"
    ],
    [
      "\u03ae\u03c4\u03b1\u03bd",
      "was"
    ],
    [
      "\u03b4\u03b5\u03ba\u03b1\u03bf\u03c7\u03c4\u03ce",
      "eighteen"
    ],
    [
      "\u03c0\u03ae\u03c7\u03b5\u03b9\u03c2",
      "cubits"
    ],
    [
      "\u03ba\u03b1\u03b9",
      "and"
    ],
    [
      "\u03c3\u03c4\u03b7\u03bd",
      "at the"
    ],
    [
      "\u03ba\u03bf\u03c1\u03c5\u03c6\u03ae",
      "top"
    ],
    [
      "\u03c4\u03bf\u03c5",
      "of the"
    ],
    [
      "\u03c5\u03c0\u03ae\u03c1\u03c7\u03b5",
      "there was"
    ],
    [
      "\u03ad\u03bd\u03b1",
      "a"
    ],
    [
      "\u03c7\u03ac\u03bb\u03ba\u03b9\u03bd\u03bf",
      "bronze"
    ],
    [
      "\u03ba\u03b9\u03bf\u03bd\u03cc\u03ba\u03c1\u03b1\u03bd\u03bf",
      "capital."
    ],
    [
      "\u03a4\u03bf",
      "The"
    ],
    [
      "\u03cd\u03c8\u03bf\u03c2",
      "height"
    ],
    [
      "\u03c4\u03bf\u03c5",
      "of the"
    ],
    [
      "\u03ba\u03b9\u03bf\u03bd\u03cc\u03ba\u03c1\u03b1\u03bd\u03bf\u03c5",
      "capital"
    ],
    [
      "\u03ae\u03c4\u03b1\u03bd",
      "was"
    ],
    [
      "\u03c4\u03c1\u03b5\u03b9\u03c2",
      "three"
    ],
    [
      "\u03c0\u03ae\u03c7\u03b5\u03b9\u03c2",
      "cubits"
    ],
    [
      "\u03ba\u03b1\u03b9",
      "and"
    ],
    [
      "\u03ae\u03c4\u03b1\u03bd",
      "was"
    ],
    [
      "\u03b4\u03b9\u03b1\u03ba\u03bf\u03c3\u03bc\u03b7\u03bc\u03ad\u03bd\u03bf",
      "decorated"
    ],
    [
      "\u03bc\u03b5",
      "with"
    ],
    [
      "\u03b4\u03b9\u03ba\u03c4\u03c5\u03c9\u03c4\u03cc",
      "lattice"
    ],
    [
      "\u03ba\u03b1\u03b9",
      "and"
    ],
    [
      "\u03c1\u03cc\u03b4\u03b9\u03b1",
      "pomegranates"
    ],
    [
      "\u03bf\u03bb\u03cc\u03b3\u03c5\u03c1\u03b1,",
      "all around,"
    ],
    [
      "\u03cc\u03bb\u03b1",
      "all"
    ],
    [
      "\u03b1\u03c0\u03cc",
      "from"
    ],
    [
      "\u03c7\u03b1\u03bb\u03ba\u03cc.",
      "copper."
    ],
    [
      "\u039f\u03b9",
      "The"
    ],
    [
      "\u03b4\u03cd\u03bf",
      "two"
    ],
    [
      "\u03c3\u03c4\u03cd\u03bb\u03bf\u03b9",
      "columns"
    ],
    [
      "\u03ba\u03b1\u03b9",
      "and"
    ],
    [
      "\u03c4\u03b1",
      "the"
    ],
    [
      "\u03b4\u03b9\u03ba\u03c4\u03c5\u03c9\u03c4\u03ac",
      "lattices"
    ],
    [
      "\u03ae\u03c4\u03b1\u03bd",
      "were"
    ],
    [
      "\u03c0\u03b1\u03bd\u03bf\u03bc\u03bf\u03b9\u03cc\u03c4\u03c5\u03c0\u03b1.",
      "identical."
    ]
  ],
  "18": [
    [
      "\u039f",
      "The"
    ],
    [
      "\u03b1\u03c1\u03c7\u03b7\u03b3\u03cc\u03c2",
      "leader"
    ],
    [
      "\u03c4\u03b7\u03c2",
      "of the"
    ],
    [
      "\u03c3\u03c9\u03bc\u03b1\u03c4\u03bf\u03c6\u03c5\u03bb\u03b1\u03ba\u03ae\u03c2",
      "bodyguard"
    ],
    [
      "\u03c3\u03c5\u03bd\u03ad\u03bb\u03b1\u03b2\u03b5",
      "arrested"
    ],
    [
      "\u03c4\u03bf\u03bd",
      "the"
    ],
    [
      "\u03b1\u03c1\u03c7\u03b9\u03b5\u03c1\u03ad\u03b1",
      "high priest"
    ],
    [
      "\u03a3\u03b5\u03c1\u03b1\u0390\u03b1",
      "Seraiah"
    ],
    [
      ",",
      ""
    ],
    [
      ",",
      ""
    ],
    [
      "\u03c4\u03bf",
      "the"
    ],
    [
      "\u03b4\u03b5\u03cd\u03c4\u03b5\u03c1\u03bf",
      "second"
    ],
    [
      "\u03c3\u03c4\u03b7\u03bd",
      "in the"
    ],
    [
      "\u03b9\u03b5\u03c1\u03b1\u03c1\u03c7\u03af\u03b1",
      "hierarchy"
    ],
    [
      "\u03b9\u03b5\u03c1\u03ad\u03b1",
      "priest"
    ],
    [
      "\u03a3\u03bf\u03c6\u03bf\u03bd\u03af\u03b1",
      "Sophonias"
    ],
    [
      ",",
      ""
    ],
    [
      ",",
      ""
    ],
    [
      "\u03ba\u03b1\u03b9",
      "and"
    ],
    [
      "\u03c4\u03bf\u03c5\u03c2",
      "the"
    ],
    [
      "\u03c4\u03c1\u03b5\u03b9\u03c2",
      "three"
    ],
    [
      "\u03c6\u03c1\u03bf\u03c5\u03c1\u03bf\u03cd\u03c2",
      "guards"
    ],
    [
      "\u03c4\u03b7\u03c2",
      "of the"
    ],
    [
      "\u03c0\u03cd\u03bb\u03b7\u03c2",
      "gate"
    ],
    [
      "\u03c4\u03bf\u03c5",
      "of the"
    ],
    [
      "\u03bd\u03b1\u03bf\u03cd",
      "temple . ."
    ]
  ],
  "19": [
    [
      "\u0395\u03c0\u03af\u03c3\u03b7\u03c2",
      "Also"
    ],
    [
      "\u03b1\u03c0\u03cc",
      "from"
    ],
    [
      "\u03c4\u03b7\u03bd",
      "the"
    ],
    [
      "\u03c0\u03cc\u03bb\u03b7",
      "city"
    ],
    [
      "\u03c3\u03c5\u03bd\u03ad\u03bb\u03b1\u03b2\u03b5",
      "arrested"
    ],
    [
      "\u03ad\u03bd\u03b1\u03bd",
      "a"
    ],
    [
      "\u03b1\u03be\u03b9\u03c9\u03bc\u03b1\u03c4\u03bf\u03cd\u03c7\u03bf",
      "officer"
    ],
    [
      "\u03b5\u03c0\u03b9\u03ba\u03b5\u03c6\u03b1\u03bb\u03ae\u03c2",
      "head"
    ],
    [
      "\u03c4\u03c9\u03bd",
      "of the"
    ],
    [
      "\u03c0\u03bf\u03bb\u03b5\u03bc\u03b9\u03c3\u03c4\u03ce\u03bd",
      "warriors"
    ],
    [
      "\u03ba\u03b1\u03b9",
      "and"
    ],
    [
      "\u03c0\u03ad\u03bd\u03c4\u03b5",
      "five"
    ],
    [
      "\u03ac\u03bd\u03c4\u03c1\u03b5\u03c2",
      "men"
    ],
    [
      "\u03b1\u03c0\u03cc",
      "from"
    ],
    [
      "\u03c4\u03bf\u03c5\u03c2",
      "the"
    ],
    [
      "\u03c0\u03c1\u03bf\u03c3\u03c9\u03c0\u03b9\u03ba\u03bf\u03cd\u03c2",
      "personal"
    ],
    [
      "\u03c3\u03c5\u03bc\u03b2\u03bf\u03cd\u03bb\u03bf\u03c5\u03c2",
      "counselors"
    ],
    [
      "\u03c4\u03bf\u03c5",
      "of the"
    ],
    [
      "\u03b2\u03b1\u03c3\u03b9\u03bb\u03b9\u03ac",
      "king"
    ],
    [
      "\u03c0\u03bf\u03c5",
      "who"
    ],
    [
      "\u03b2\u03c1\u03af\u03c3\u03ba\u03bf\u03bd\u03c4\u03b1\u03bd",
      "were"
    ],
    [
      "\u03c3\u03c4\u03b7\u03bd",
      "in the"
    ],
    [
      "\u0399\u03b5\u03c1\u03bf\u03c5\u03c3\u03b1\u03bb\u03ae\u03bc",
      "Jerusalem"
    ],
    [
      "\u03c4\u03bf",
      "the"
    ],
    [
      "\u03b3\u03c1\u03b1\u03bc\u03bc\u03b1\u03c4\u03ad\u03b1",
      "secretary"
    ],
    [
      "\u03c4\u03bf\u03c5",
      "of the"
    ],
    [
      "\u03b1\u03c1\u03c7\u03b9\u03c3\u03c4\u03c1\u03ac\u03c4\u03b7\u03b3\u03bf\u03c5",
      "commander"
    ],
    [
      "\u03c0\u03bf\u03c5",
      "who"
    ],
    [
      "\u03ae\u03c4\u03b1\u03bd",
      "was"
    ],
    [
      "\u03c5\u03c0\u03b5\u03cd\u03b8\u03c5\u03bd\u03bf\u03c2",
      "responsible"
    ],
    [
      "\u03b3\u03b9\u03b1",
      "for"
    ],
    [
      "\u03c4\u03b7",
      "the"
    ],
    [
      "\u03c3\u03c4\u03c1\u03b1\u03c4\u03bf\u03bb\u03cc\u03b3\u03b7\u03c3\u03b7",
      "recruitment"
    ],
    [
      "\u03c4\u03c9\u03bd",
      "of the"
    ],
    [
      "\u03b1\u03bd\u03c4\u03c1\u03ce\u03bd",
      "men"
    ],
    [
      "\u03ba\u03b1\u03b8\u03ce\u03c2",
      "as well as"
    ],
    [
      "\u03ba\u03b9",
      "and"
    ],
    [
      "\u03b5\u03be\u03ae\u03bd\u03c4\u03b1",
      "sixty"
    ],
    [
      "\u03ac\u03bd\u03c4\u03c1\u03b5\u03c2",
      "men"
    ],
    [
      "\u03b1\u03c0\u03cc",
      "from"
    ],
    [
      "\u03c4\u03bf\u03c5\u03c2",
      "the"
    ],
    [
      "\u03ba\u03b1\u03c4\u03bf\u03af\u03ba\u03bf\u03c5\u03c2",
      "inhabitants"
    ],
    [
      "\u03c4\u03b7\u03c2",
      "of the"
    ],
    [
      "\u03c0\u03cc\u03bb\u03b7\u03c2",
      "city"
    ]
  ],
  "20": [
    [
      "\u039f",
      "The"
    ],
    [
      "\u039d\u03b5\u03b2\u03bf\u03c5\u03b6\u03b1\u03c1\u03b1\u03b4\u03ac\u03bd",
      "Nebuzaradan"
    ],
    [
      "\u03c4\u03bf\u03c5\u03c2",
      "them"
    ],
    [
      "\u03ad\u03c6\u03b5\u03c1\u03b5",
      "brought"
    ],
    [
      "\u03c3\u03c4\u03bf\u03bd",
      "to the"
    ],
    [
      "\u03b2\u03b1\u03c3\u03b9\u03bb\u03b9\u03ac",
      "king"
    ],
    [
      "\u03c4\u03b7\u03c2",
      "of the"
    ],
    [
      "\u0392\u03b1\u03b2\u03c5\u03bb\u03ce\u03bd\u03b1\u03c2",
      "Babylon"
    ],
    [
      "\u03c3\u03c4\u03b7",
      "at the"
    ],
    [
      "\u03a1\u03b9\u03b2\u03bb\u03ac",
      "Riblah"
    ]
  ],
  "21": [
    [
      "#",
      "VALUE!"
    ]
  ],
  "22": [
    [
      "\u039f",
      "The"
    ],
    [
      "\u03b2\u03b1\u03c3\u03b9\u03bb\u03b9\u03ac\u03c2",
      "king"
    ],
    [
      "\u03c4\u03b7\u03c2",
      "of the"
    ],
    [
      "\u0392\u03b1\u03b2\u03c5\u03bb\u03ce\u03bd\u03b1\u03c2",
      "Babylon"
    ],
    [
      "\u039d\u03b1\u03b2\u03bf\u03c5\u03c7\u03bf\u03b4\u03bf\u03bd\u03cc\u03c3\u03bf\u03c1",
      "Nebuchadnezzar"
    ],
    [
      "\u03ac\u03c6\u03b7\u03c3\u03b5",
      "left"
    ],
    [
      "\u03c3\u03c4\u03b7",
      "in the"
    ],
    [
      "\u03c7\u03ce\u03c1\u03b1",
      "country"
    ],
    [
      "\u03c4\u03bf\u03c5",
      "of"
    ],
    [
      "\u0399\u03bf\u03cd\u03b4\u03b1",
      "Judah"
    ],
    [
      "\u03ad\u03bd\u03b1",
      "a"
    ],
    [
      "\u03bc\u03ad\u03c1\u03bf\u03c2",
      "part"
    ],
    [
      "\u03c4\u03bf\u03c5",
      "of the"
    ],
    [
      "\u03c0\u03bb\u03b7\u03b8\u03c5\u03c3\u03bc\u03bf\u03cd",
      "population."
    ],
    [
      "\u03a3\u2019",
      "To these"
    ],
    [
      "\u03b1\u03c5\u03c4\u03bf\u03cd\u03c2",
      "these"
    ],
    [
      "\u03b4\u03b9\u03cc\u03c1\u03b9\u03c3\u03b5",
      "he appointed"
    ],
    [
      "\u03ba\u03c5\u03b2\u03b5\u03c1\u03bd\u03ae\u03c4\u03b7",
      "governor"
    ],
    [
      "\u03c4\u03bf",
      "the"
    ],
    [
      "\u0393\u03b5\u03b4\u03b1\u03bb\u03af\u03b1",
      "Gedaliah,"
    ],
    [
      "\u03b3\u03b9\u03bf",
      "son"
    ],
    [
      "\u03c4\u03bf\u03c5",
      "of"
    ],
    [
      "\u0391\u03c7\u03b9\u03ba\u03ac\u03bc",
      "Ahikam"
    ],
    [
      "\u03ba\u03b1\u03b9",
      "and"
    ],
    [
      "\u03b5\u03b3\u03b3\u03bf\u03bd\u03cc",
      "grandson"
    ],
    [
      "\u03c4\u03bf\u03c5",
      "of"
    ],
    [
      "\u03a3\u03b1\u03c6\u03ac\u03bd",
      "Shaphan."
    ]
  ],
  "23": [
    [
      "\u038c\u03c4\u03b1\u03bd",
      "When"
    ],
    [
      "\u03bf\u03b9",
      "the"
    ],
    [
      "\u03b1\u03c1\u03c7\u03b7\u03b3\u03bf\u03af",
      "leaders"
    ],
    [
      "\u03c4\u03c9\u03bd",
      "of the"
    ],
    [
      "\u03c3\u03c4\u03c1\u03b1\u03c4\u03b5\u03c5\u03bc\u03ac\u03c4\u03c9\u03bd",
      "armies"
    ],
    [
      "\u03c0\u03bf\u03c5",
      "who"
    ],
    [
      "\u03b5\u03af\u03c7\u03b1\u03bd",
      "had"
    ],
    [
      "\u03b4\u03b9\u03b1\u03c6\u03cd\u03b3\u03b5\u03b9",
      "escaped"
    ],
    [
      "\u03c4\u03b7\u03bd",
      "the"
    ],
    [
      "\u03b1\u03b9\u03c7\u03bc\u03b1\u03bb\u03c9\u03c3\u03af\u03b1",
      "captivity"
    ],
    [
      "\u03ac\u03ba\u03bf\u03c5\u03c3\u03b1\u03bd",
      "heard"
    ],
    [
      "\u03cc\u03c4\u03b9",
      "that"
    ],
    [
      "\u03bf",
      "the"
    ],
    [
      "\u03b2\u03b1\u03c3\u03b9\u03bb\u03b9\u03ac\u03c2",
      "king"
    ],
    [
      "\u03c4\u03b7\u03c2",
      "of the"
    ],
    [
      "\u0392\u03b1\u03b2\u03c5\u03bb\u03ce\u03bd\u03b1\u03c2",
      "Babylon"
    ],
    [
      "\u03b4\u03b9\u03cc\u03c1\u03b9\u03c3\u03b5",
      "appointed"
    ],
    [
      "\u03ba\u03c5\u03b2\u03b5\u03c1\u03bd\u03ae\u03c4\u03b7",
      "governor"
    ],
    [
      "\u03c4\u03bf",
      "the"
    ],
    [
      "\u0393\u03b5\u03b4\u03b1\u03bb\u03af\u03b1,",
      "Gedaliah,"
    ],
    [
      "\u03ae\u03c1\u03b8\u03b1\u03bd",
      "came"
    ],
    [
      "\u03c3\u2019",
      "to"
    ],
    [
      "\u03b1\u03c5\u03c4\u03cc\u03bd",
      "him"
    ],
    [
      "\u03bc\u03b1\u03b6\u03af",
      "together"
    ],
    [
      "\u03bc\u03b5",
      "with"
    ],
    [
      "\u03c4\u03bf\u03c5\u03c2",
      "their"
    ],
    [
      "\u03ac\u03bd\u03c4\u03c1\u03b5\u03c2",
      "men"
    ],
    [
      "\u03c4\u03bf\u03c5\u03c2,",
      "their,"
    ],
    [
      "\u03c3\u03c4\u03b7",
      "at the"
    ],
    [
      "\u039c\u03b9\u03c3\u03c0\u03ac.",
      "Mizpah."
    ],
    [
      "\u0389\u03c4\u03b1\u03bd",
      "There were"
    ],
    [
      "\u03bf",
      "the"
    ],
    [
      "\u0399\u03c3\u03bc\u03b1\u03ae\u03bb,",
      "Ishmael,"
    ],
    [
      "\u03b3\u03b9\u03bf\u03c2",
      "son"
    ],
    [
      "\u03c4\u03bf\u03c5",
      "of"
    ],
    [
      "\u039d\u03b5\u03b8\u03b1\u03bd\u03af\u03b1,",
      "Nethaniah,"
    ],
    [
      "\u03bf",
      "the"
    ],
    [
      "\u0399\u03c9\u03c7\u03b1\u03bd\u03ac\u03bd,",
      "Johanan,"
    ],
    [
      "\u03b3\u03b9\u03bf\u03c2",
      "son"
    ],
    [
      "\u03c4\u03bf\u03c5",
      "of"
    ],
    [
      "\u039a\u03b1\u03c1\u03b5\u03ac\u03c7,",
      "Kareah,"
    ],
    [
      "\u03bf",
      "the"
    ],
    [
      "\u03a3\u03b5\u03c1\u03b1\u0390\u03b1\u03c2,",
      "Seriah,"
    ],
    [
      "\u03b3\u03b9\u03bf\u03c2",
      "son"
    ],
    [
      "\u03c4\u03bf\u03c5",
      "of"
    ],
    [
      "\u03a4\u03b1\u03bd\u03c7\u03bf\u03c5\u03bc\u03ad\u03b8",
      "Tanhumeth"
    ],
    [
      "\u03c4\u03bf\u03c5",
      "of"
    ],
    [
      "\u039d\u03b5\u03c4\u03c9\u03c6\u03b1\u03b8\u03af\u03c4\u03b7",
      "Netophathite"
    ],
    [
      "\u03ba\u03b1\u03b9",
      "and"
    ],
    [
      "\u03bf",
      "the"
    ],
    [
      "\u0399\u03b1\u03b1\u03b6\u03b1\u03bd\u03af\u03b1\u03c2,",
      "Jaaazaniah,"
    ],
    [
      "\u03b3\u03b9\u03bf\u03c2",
      "son"
    ],
    [
      "\u03ba\u03ac\u03c0\u03bf\u03b9\u03bf\u03c5",
      "of some"
    ],
    [
      "\u039c\u03b1\u03b1\u03c7\u03b1\u03b8\u03af\u03c4\u03b7.",
      "Maachathite."
    ]
  ],
  "24": [
    [
      "\u039f",
      "The"
    ],
    [
      "\u0393\u03b5\u03b4\u03b1\u03bb\u03af\u03b1\u03c2",
      "Gedaliah"
    ],
    [
      "\u03bf\u03c1\u03ba\u03af\u03c3\u03c4\u03b7\u03ba\u03b5",
      "swore"
    ],
    [
      "\u03bc\u03c0\u03c1\u03bf\u03c3\u03c4\u03ac",
      "in front"
    ],
    [
      "\u03c4\u03bf\u03c5\u03c2",
      "of them"
    ],
    [
      "\u03ba\u03b1\u03b9",
      "and"
    ],
    [
      "\u03bc\u03c0\u03c1\u03bf\u03c3\u03c4\u03ac",
      "in front"
    ],
    [
      "\u03c3\u03c4\u03bf\u03c5\u03c2",
      "to the"
    ],
    [
      "\u03ac\u03bd\u03c4\u03c1\u03b5\u03c2",
      "men"
    ],
    [
      "\u03c4\u03bf\u03c5\u03c2",
      "their"
    ],
    [
      "\u03ba\u03b1\u03b9",
      "and"
    ],
    [
      "\u03c4\u03bf\u03c5\u03c2",
      "to them"
    ],
    [
      "\u03b5\u03af\u03c0\u03b5",
      "said"
    ],
    [
      "\u039c\u03b7",
      "Do not"
    ],
    [
      "\u03c6\u03bf\u03b2\u03ac\u03c3\u03c4\u03b5",
      "fear"
    ],
    [
      "\u03b1\u03c0\u03cc",
      "from"
    ],
    [
      "\u03c4\u03bf\u03c5\u03c2",
      "the"
    ],
    [
      "\u03b1\u03be\u03b9\u03c9\u03bc\u03b1\u03c4\u03bf\u03cd\u03c7\u03bf\u03c5\u03c2",
      "officials"
    ],
    [
      "\u03c4\u03c9\u03bd",
      "of the"
    ],
    [
      "\u0392\u03b1\u03b2\u03c5\u03bb\u03c9\u03bd\u03af\u03c9\u03bd",
      "Babylonians"
    ],
    [
      "\u0387",
      ""
    ],
    [
      ";",
      ""
    ],
    [
      "\u03b5\u03b3\u03ba\u03b1\u03c4\u03b1\u03c3\u03c4\u03b1\u03b8\u03b5\u03af\u03c4\u03b5",
      "settle"
    ],
    [
      "\u03c3\u03c4\u03b7",
      "in the"
    ],
    [
      "\u03c7\u03ce\u03c1\u03b1",
      "land"
    ],
    [
      "\u03ba\u03b1\u03b9",
      "and"
    ],
    [
      "\u03c5\u03c0\u03bf\u03c4\u03b1\u03c7\u03b8\u03b5\u03af\u03c4\u03b5",
      "submit"
    ],
    [
      "\u03c3\u03c4\u03bf",
      "to the"
    ],
    [
      "\u03b2\u03b1\u03c3\u03b9\u03bb\u03b9\u03ac",
      "king"
    ],
    [
      "\u03c4\u03b7\u03c2",
      "of the"
    ],
    [
      "\u0392\u03b1\u03b2\u03c5\u03bb\u03ce\u03bd\u03b1\u03c2",
      "Babylon"
    ],
    [
      "\u03ba\u03b9",
      "and"
    ],
    [
      "\u03b1\u03c5\u03c4\u03cc",
      "this"
    ],
    [
      "\u03b8\u03b1",
      "will"
    ],
    [
      "\u03c3\u03b1\u03c2",
      "to you"
    ],
    [
      "\u03b2\u03b3\u03b5\u03b9",
      "turn out"
    ],
    [
      "\u03c3\u03b5",
      "to"
    ],
    [
      "\u03ba\u03b1\u03bb\u03cc",
      "good"
    ]
  ],
  "25": [
    [
      "\u0391\u03bb\u03bb\u03ac",
      "But"
    ],
    [
      "\u03c4\u03bf\u03bd",
      "the"
    ],
    [
      "\u03ad\u03b2\u03b4\u03bf\u03bc\u03bf",
      "seventh"
    ],
    [
      "\u03bc\u03ae\u03bd\u03b1",
      "month"
    ],
    [
      "\u03ae\u03c1\u03b8\u03b5",
      "came"
    ],
    [
      "\u03bf",
      "the"
    ],
    [
      "\u0399\u03c3\u03bc\u03b1\u03ae\u03bb,",
      "Ishmael,"
    ],
    [
      "\u03b3\u03b9\u03bf\u03c2",
      "son"
    ],
    [
      "\u03c4\u03bf\u03c5",
      "of the"
    ],
    [
      "\u039d\u03b5\u03b8\u03b1\u03bd\u03af\u03b1",
      "Nethaniah"
    ],
    [
      "\u03ba\u03b9",
      "and"
    ],
    [
      "\u03b5\u03b3\u03b3\u03bf\u03bd\u03cc\u03c2",
      "grandson"
    ],
    [
      "\u03c4\u03bf\u03c5",
      "of the"
    ],
    [
      "\u0395\u03bb\u03b9\u03c3\u03b1\u03bc\u03ac,",
      "Elishama,"
    ],
    [
      "\u03c0\u03bf\u03c5",
      "who"
    ],
    [
      "\u03ba\u03b1\u03c4\u03b1\u03b3\u03cc\u03bd\u03c4\u03b1\u03bd",
      "descended"
    ],
    [
      "\u03b1\u03c0\u03cc",
      "from"
    ],
    [
      "\u03c4\u03b7",
      "the"
    ],
    [
      "\u03b2\u03b1\u03c3\u03b9\u03bb\u03b9\u03ba\u03ae",
      "royal"
    ],
    [
      "\u03bf\u03b9\u03ba\u03bf\u03b3\u03ad\u03bd\u03b5\u03b9\u03b1,",
      "family,"
    ],
    [
      "\u03bc\u03b1\u03b6\u03af",
      "together"
    ],
    [
      "\u03bc\u03b5",
      "with"
    ],
    [
      "\u03b4\u03ad\u03ba\u03b1",
      "ten"
    ],
    [
      "\u03ac\u03bd\u03c4\u03c1\u03b5\u03c2,",
      "men,"
    ],
    [
      "\u03ba\u03b1\u03b9",
      "and"
    ],
    [
      "\u03b8\u03b1\u03bd\u03ac\u03c4\u03c9\u03c3\u03b1\u03bd",
      "they killed"
    ],
    [
      "\u03c4\u03bf",
      "the"
    ],
    [
      "\u0393\u03b5\u03b4\u03b1\u03bb\u03af\u03b1,",
      "Gedaliah,"
    ],
    [
      "\u03ba\u03b1\u03b8\u03ce\u03c2",
      "as"
    ],
    [
      "\u03ba\u03b1\u03b9",
      "also"
    ],
    [
      "\u03c4\u03bf\u03c5\u03c2",
      "the"
    ],
    [
      "\u03ac\u03bd\u03c4\u03c1\u03b5\u03c2",
      "men"
    ],
    [
      "\u03c4\u03bf\u03c5",
      "of"
    ],
    [
      "\u0399\u03bf\u03cd\u03b4\u03b1",
      "Judah"
    ],
    [
      "\u03ba\u03b1\u03b9",
      "and"
    ],
    [
      "\u03c4\u03bf\u03c5\u03c2",
      "the"
    ],
    [
      "\u0392\u03b1\u03b2\u03c5\u03bb\u03ce\u03bd\u03b9\u03bf\u03c5\u03c2",
      "Babylonians"
    ],
    [
      "\u03c0\u03bf\u03c5",
      "who"
    ],
    [
      "\u03ae\u03c4\u03b1\u03bd",
      "were"
    ],
    [
      "\u03c3\u03c4\u03bf",
      "in the"
    ],
    [
      "\u03c3\u03c0\u03af\u03c4\u03b9",
      "house"
    ],
    [
      "\u03c4\u03bf\u03c5",
      "of him"
    ],
    [
      "\u03c3\u03c4\u03b7",
      "in the"
    ],
    [
      "\u039c\u03b9\u03c3\u03c0\u03ac.",
      "Mizpah."
    ]
  ],
  "26": [
    [
      "\u03a4\u03cc\u03c4\u03b5",
      "Then"
    ],
    [
      "\u03cc\u03bb\u03bf\u03c2",
      "all"
    ],
    [
      "\u03bf",
      "the"
    ],
    [
      "\u03bb\u03b1\u03cc\u03c2",
      "people"
    ],
    [
      "\u03bc\u03b9\u03ba\u03c1\u03bf\u03af",
      "small"
    ],
    [
      "\u03ba\u03b1\u03b9",
      "and"
    ],
    [
      "\u03bc\u03b5\u03b3\u03ac\u03bb\u03bf\u03b9",
      "big"
    ],
    [
      "\u03ba\u03b1\u03b9",
      "and"
    ],
    [
      "\u03bf\u03b9",
      "the"
    ],
    [
      "\u03b1\u03c1\u03c7\u03b7\u03b3\u03bf\u03af",
      "leaders"
    ],
    [
      "\u03c4\u03c9\u03bd",
      "of the"
    ],
    [
      "\u03c3\u03c4\u03c1\u03b1\u03c4\u03b5\u03c5\u03bc\u03ac\u03c4\u03c9\u03bd",
      "armies"
    ],
    [
      "\u03be\u03b5\u03c3\u03b7\u03ba\u03ce\u03b8\u03b7\u03ba\u03b1\u03bd",
      "rose up"
    ],
    [
      "\u03ba\u03b9",
      "and"
    ],
    [
      "\u03ad\u03c6\u03c5\u03b3\u03b1\u03bd",
      "left"
    ],
    [
      "\u03b3\u03b9\u03b1",
      "for"
    ],
    [
      "\u03c4\u03b7\u03bd",
      "the"
    ],
    [
      "\u0391\u03af\u03b3\u03c5\u03c0\u03c4\u03bf",
      "Egypt"
    ],
    [
      "\u03b3\u03b9\u03b1\u03c4\u03af",
      "because"
    ],
    [
      "\u03c6\u03bf\u03b2\u03cc\u03bd\u03c4\u03bf\u03c5\u03c3\u03b1\u03bd",
      "they feared"
    ],
    [
      "\u03c4\u03bf\u03c5\u03c2",
      "the"
    ],
    [
      "\u0392\u03b1\u03b2\u03c5\u03bb\u03ce\u03bd\u03b9\u03bf\u03c5\u03c2",
      "Babylonians"
    ]
  ],
  "27": [
    [
      "\u03a4\u03c1\u03b9\u03ac\u03bd\u03c4\u03b1",
      "Thirty"
    ],
    [
      "\u03b5\u03c6\u03c4\u03ac",
      "seven"
    ],
    [
      "\u03c7\u03c1\u03cc\u03bd\u03b9\u03b1",
      "years"
    ],
    [
      "\u03b1\u03c0\u03cc",
      "from"
    ],
    [
      "\u03c4\u03b7\u03bd",
      "the"
    ],
    [
      "\u03b1\u03b9\u03c7\u03bc\u03b1\u03bb\u03c9\u03c3\u03af\u03b1",
      "captivity"
    ],
    [
      "\u03c4\u03bf\u03c5",
      "of the"
    ],
    [
      "\u0399\u03c9\u03b1\u03c7\u03af\u03bd",
      "Joaquin"
    ],
    [
      "\u03b2\u03b1\u03c3\u03b9\u03bb\u03b9\u03ac",
      "king"
    ],
    [
      "\u03c4\u03bf\u03c5",
      "of the"
    ],
    [
      "\u0399\u03bf\u03cd\u03b4\u03b1",
      "Judah"
    ],
    [
      "\u03ad\u03b3\u03b9\u03bd\u03b5",
      "became"
    ],
    [
      "\u03b2\u03b1\u03c3\u03b9\u03bb\u03b9\u03ac\u03c2",
      "king"
    ],
    [
      "\u03c4\u03b7\u03c2",
      "of the"
    ],
    [
      "\u0392\u03b1\u03b2\u03c5\u03bb\u03ce\u03bd\u03b1\u03c2",
      "Babylon"
    ],
    [
      "\u03bf",
      "the"
    ],
    [
      "\u0395\u03c5\u0390\u03bb-\u039c\u03b5\u03c1\u03c9\u03b4\u03ac\u03c7",
      "Evil-Merodach"
    ],
    [
      "\u039a\u03b1\u03b9",
      "And"
    ],
    [
      "\u03c4\u03bf\u03bd",
      "the"
    ],
    [
      "\u03af\u03b4\u03b9\u03bf",
      "same"
    ],
    [
      "\u03c7\u03c1\u03cc\u03bd\u03bf",
      "year"
    ],
    [
      "\u03c4\u03b7\u03bd",
      "the"
    ],
    [
      "\u03b5\u03b9\u03ba\u03bf\u03c3\u03c4\u03ae",
      "twentieth"
    ],
    [
      "\u03ad\u03b2\u03b4\u03bf\u03bc\u03b7",
      "seventh"
    ],
    [
      "\u03bc\u03ad\u03c1\u03b1",
      "day"
    ],
    [
      "\u03c4\u03bf\u03c5",
      "of the"
    ],
    [
      "\u03b4\u03c9\u03b4\u03ad\u03ba\u03b1\u03c4\u03bf\u03c5",
      "twelfth"
    ],
    [
      "\u03bc\u03ae\u03bd\u03b1",
      "month"
    ],
    [
      "\u03ad\u03b4\u03c9\u03c3\u03b5",
      "gave"
    ],
    [
      "\u03b1\u03bc\u03bd\u03b7\u03c3\u03c4\u03af\u03b1",
      "amnesty"
    ],
    [
      "\u03c3\u03c4\u03bf\u03bd",
      "to the"
    ],
    [
      "\u0399\u03c9\u03b1\u03c7\u03af\u03bd",
      "Joaquin"
    ],
    [
      "\u03ba\u03b1\u03b9",
      "and"
    ],
    [
      "\u03c4\u03bf\u03bd",
      "him"
    ],
    [
      "\u03ad\u03b2\u03b3\u03b1\u03bb\u03b5",
      "removed"
    ],
    [
      "\u03b1\u03c0\u03cc",
      "from"
    ],
    [
      "\u03c4\u03b7",
      "the"
    ],
    [
      "\u03c6\u03c5\u03bb\u03b1\u03ba\u03ae",
      "prison"
    ]
  ],
  "28": [
    [
      "\u03a4\u03bf\u03c5",
      "of him"
    ],
    [
      "\u03c6\u03ad\u03c1\u03b8\u03b7\u03ba\u03b5",
      "was treated"
    ],
    [
      "\u03bc\u03b5",
      "with"
    ],
    [
      "\u03b5\u03c5\u03bc\u03ad\u03bd\u03b5\u03b9\u03b1",
      "favor/kindness"
    ],
    [
      "\u03ba\u03b1\u03b9",
      "and"
    ],
    [
      "\u03c4\u03bf\u03bd",
      "him"
    ],
    [
      "\u03c4\u03af\u03bc\u03b7\u03c3\u03b5",
      "honored"
    ],
    [
      "\u03c0\u03b5\u03c1\u03b9\u03c3\u03c3\u03cc\u03c4\u03b5\u03c1\u03bf",
      "more"
    ],
    [
      "\u03b1\u03c0\u03cc",
      "than"
    ],
    [
      "\u03c4\u03bf\u03c5\u03c2",
      "the"
    ],
    [
      "\u03ac\u03bb\u03bb\u03bf\u03c5\u03c2",
      "other"
    ],
    [
      "\u03b2\u03b1\u03c3\u03b9\u03bb\u03b9\u03ac\u03b4\u03b5\u03c2",
      "kings"
    ],
    [
      "\u03c0\u03bf\u03c5",
      "who"
    ],
    [
      "\u03ae\u03c4\u03b1\u03bd",
      "were"
    ],
    [
      "\u03bc\u03b1\u03b6\u03af",
      "with"
    ],
    [
      "\u03c4\u03bf\u03c5",
      "him"
    ],
    [
      "\u03b1\u03b9\u03c7\u03bc\u03ac\u03bb\u03c9\u03c4\u03bf\u03b9",
      "captives/prisoners"
    ],
    [
      "\u03c3\u03c4\u03b7",
      "in the"
    ],
    [
      "\u0392\u03b1\u03b2\u03c5\u03bb\u03ce\u03bd\u03b1",
      "Babylon"
    ]
  ],
  "29": [
    [
      "\u0388\u03c4\u03c3\u03b9",
      "Thus"
    ],
    [
      "\u03c4\u03bf\u03c5",
      "to him"
    ],
    [
      "\u03b5\u03c0\u03b9\u03c4\u03c1\u03ac\u03c0\u03b7\u03ba\u03b5",
      "was allowed"
    ],
    [
      "\u03bd\u03b1",
      "to"
    ],
    [
      "\u03b2\u03b3\u03ac\u03bb\u03b5\u03b9",
      "take out"
    ],
    [
      "\u03c4\u03b1",
      "the"
    ],
    [
      "\u03c1\u03bf\u03cd\u03c7\u03b1",
      "clothes"
    ],
    [
      "\u03c4\u03b7\u03c2",
      "of the"
    ],
    [
      "\u03c6\u03c5\u03bb\u03b1\u03ba\u03ae\u03c2",
      "prison"
    ],
    [
      "\u03ba\u03b1\u03b9",
      "and"
    ],
    [
      "\u03bd\u03b1",
      "to"
    ],
    [
      "\u03c3\u03c5\u03bd\u03c4\u03c1\u03ce\u03b3\u03b5\u03b9",
      "eat together"
    ],
    [
      "\u03bc\u03b5",
      "with"
    ],
    [
      "\u03c4\u03bf",
      "the"
    ],
    [
      "\u03b2\u03b1\u03c3\u03b9\u03bb\u03b9\u03ac",
      "king"
    ],
    [
      "\u03c4\u03bf",
      "the"
    ],
    [
      "\u03c5\u03c0\u03cc\u03bb\u03bf\u03b9\u03c0\u03bf",
      "rest"
    ],
    [
      "\u03c4\u03b7\u03c2",
      "of the"
    ],
    [
      "\u03b6\u03c9\u03ae\u03c2",
      "life"
    ],
    [
      "\u03c4\u03bf\u03c5",
      "his"
    ]
  ],
  "30": [
    [
      "\u0395\u03c0\u03af\u03c3\u03b7\u03c2",
      "Also"
    ],
    [
      "\u03cc\u03c3\u03bf",
      "as long as"
    ],
    [
      "\u03b6\u03bf\u03cd\u03c3\u03b5",
      "lived"
    ],
    [
      "\u03c4\u03bf\u03c5",
      "to him"
    ],
    [
      "\u03c0\u03b1\u03c1\u03ad\u03c7\u03bf\u03bd\u03c4\u03b1\u03bd",
      "were provided"
    ],
    [
      "\u03ba\u03ac\u03b8\u03b5",
      "every"
    ],
    [
      "\u03bc\u03ad\u03c1\u03b1",
      "day"
    ],
    [
      "\u03b1\u03c0\u03cc",
      "from"
    ],
    [
      "\u03c4\u03bf",
      "the"
    ],
    [
      "\u03b2\u03b1\u03c3\u03b9\u03bb\u03b9\u03ac",
      "king"
    ],
    [
      "\u03c4\u03b7\u03c2",
      "of the"
    ],
    [
      "\u0392\u03b1\u03b2\u03c5\u03bb\u03ce\u03bd\u03b1\u03c2",
      "Babylon"
    ],
    [
      "\u03cc\u03bb\u03b1",
      "all"
    ],
    [
      "\u03c4\u03b1",
      "the"
    ],
    [
      "\u03b1\u03c0\u03b1\u03c1\u03b1\u03af\u03c4\u03b7\u03c4\u03b1",
      "necessary"
    ],
    [
      "\u03b3\u03b9\u03b1",
      "for"
    ],
    [
      "\u03c4\u03b7",
      "the"
    ],
    [
      "\u03c3\u03c5\u03bd\u03c4\u03ae\u03c1\u03b7\u03c3\u03ae",
      "maintenance"
    ],
    [
      "\u03c4\u03bf\u03c5",
      "his"
    ]
  ]
}